[
  {
    "ts": "2020-01-05T16:44:50.804Z",
    "level": "error",
    "error": {
      "originalError": {
        "name": "AccessTokenInvalid",
        "message": "{\n  \"status\": 403,\n  \"statusText\": \"Forbidden\",\n  \"message\": \"The access token you sent could not be found or is invalid.\",\n  \"details\": {},\n  \"request\": {\n    \"url\": \"https://api.contentful.com:443/spaces/96iucuiaj1p3\",\n    \"headers\": {\n      \"Accept\": \"application/json, text/plain, */*\",\n      \"Content-Type\": \"application/vnd.contentful.management.v1+json\",\n      \"X-Contentful-User-Agent\": \"app contentful.import/7.6.2; feature library-import; sdk contentful-management.js/5.12.0; platform node.js/v11.14.0; os macOS/18.7.0;\",\n      \"Authorization\": \"Bearer ...Z4wXw\",\n      \"user-agent\": \"node.js/v11.14.0\",\n      \"Accept-Encoding\": \"gzip\"\n    },\n    \"method\": \"get\"\n  },\n  \"requestId\": \"979ba5023b197fc86df4a44951cbb4af\"\n}"
      },
      "data": {
        "status": 403,
        "statusText": "Forbidden",
        "message": "The access token you sent could not be found or is invalid.",
        "details": {},
        "request": {
          "url": "https://api.contentful.com:443/spaces/96iucuiaj1p3",
          "headers": {
            "Accept": "application/json, text/plain, */*",
            "Content-Type": "application/vnd.contentful.management.v1+json",
            "X-Contentful-User-Agent": "app contentful.import/7.6.2; feature library-import; sdk contentful-management.js/5.12.0; platform node.js/v11.14.0; os macOS/18.7.0;",
            "Authorization": "Bearer ...Z4wXw",
            "user-agent": "node.js/v11.14.0",
            "Accept-Encoding": "gzip"
          },
          "method": "get"
        },
        "requestId": "979ba5023b197fc86df4a44951cbb4af"
      }
    }
  }
]
